lichens/.DS_Store
lichens/__init__.py
lichens/__main__.py
lichens/config/__init__.py
lichens/db/__init__.py
lichens/db/connection.py
lichens/db/migrations/README
lichens/db/migrations/alembic.ini
lichens/db/migrations/env.py
lichens/db/migrations/script.py.mako
lichens/db/models.py
lichens/db/utils.py
lichens/errors/__init__.py
lichens/errors/db_errors.py
lichens/errors/file_errors.py
lichens/logging/__init__.py
lichens/logging/_logger.py
lichens/manager/__init__.py
lichens/manager/manager.py
lichens/tools/__init__.py
lichens/tools/tools.py
lichens/utils/__init__.py
lichens/utils/utils.py
lichens/validator/__init__.py
lichens-0.1.0.dist-info/LICENSE
lichens-0.1.0.dist-info/METADATA
lichens-0.1.0.dist-info/WHEEL
lichens-0.1.0.dist-info/RECORD
