Metadata-Version: 2.1
Name: lichens
Version: 0.1.0
Summary: ETL framework for Colosscious Pharmquer
License: MIT
Author: thisishugow
Author-email: 59921505+thisishugow@users.noreply.github.com
Requires-Python: >=3.10,<3.13
Classifier: License :: OSI Approved :: MIT License
Classifier: Programming Language :: Python :: 3
Classifier: Programming Language :: Python :: 3.10
Classifier: Programming Language :: Python :: 3.11
Requires-Dist: alembic (>=1.12.1,<2.0.0)
Requires-Dist: click (>=8.1.7,<9.0.0)
Requires-Dist: crontab (>=1.0.1,<2.0.0)
Requires-Dist: pandas (>=2.1.3,<3.0.0)
Requires-Dist: pandera (>=0.17.2,<0.18.0)
Requires-Dist: pendulum (==2.1.2)
Requires-Dist: psycopg-binary (>=3.1.12,<4.0.0)
Requires-Dist: psycopg2-binary (>=2.9.9,<3.0.0)
Requires-Dist: sqlalchemy (>=2.0.23,<3.0.0)
